{
  "preRequisites:11": [
    90103
  ],
  "properties:10": {
    "betterquesting:10": {
      "desc:8": "§7§o这些能量单元性能不算太好，但能以较低传输速率无限传输能量！",
      "icon:10": {
        "Count:3": 1,
        "id:8": "rftools:powercell"
      },
      "name:8": "能量单元"
    }
  },
  "questID:3": 722,
  "tasks:9": {
    "0:10": {
      "index:3": 0,
      "requiredItems:9": {
        "0:10": {
          "Count:3": 1,
          "id:8": "rftools:powercell"
        }
      },
      "taskID:8": "bq_standard:retrieval"
    }
  }
}