{
  "preRequisites:11": [
    90083
  ],
  "properties:10": {
    "betterquesting:10": {
      "desc:8": "§7§o可存储16桶流体。",
      "icon:10": {
        "Count:3": 1,
        "id:8": "enderio:block_tank",
        "tag:10": {
          "enderio:data:10": {
            "tank:10": {
              "Capacity:3": 16000,
              "Empty:8": ""
            }
          }
        }
      },
      "name:8": "流体储罐"
    }
  },
  "questID:3": 90091,
  "tasks:9": {
    "0:10": {
      "ignoreNBT:1": 1,
      "index:3": 0,
      "requiredItems:9": {
        "0:10": {
          "Count:3": 1,
          "id:8": "enderio:block_tank",
          "tag:10": {
            "enderio:data:10": {
              "tank:10": {
                "Capacity:3": 16000,
                "Empty:8": ""
              }
            }
          }
        }
      },
      "taskID:8": "bq_standard:retrieval"
    }
  }
}