{
  "preRequisites:11": [
    90131
  ],
  "properties:10": {
    "betterquesting:10": {
      "desc:8": "§7§o网络工具能查看网络中连接的设备数量，以及能量消耗！\n\n右击ME控制器以查看！",
      "icon:10": {
        "Count:3": 1,
        "id:8": "appliedenergistics2:network_tool"
      },
      "name:8": "网络工具"
    }
  },
  "questID:3": 90189,
  "tasks:9": {
    "0:10": {
      "index:3": 0,
      "requiredItems:9": {
        "0:10": {
          "Count:3": 1,
          "id:8": "appliedenergistics2:network_tool"
        }
      },
      "taskID:8": "bq_standard:retrieval"
    }
  }
}