{
  "preRequisites:11": [
    90196
  ],
  "properties:10": {
    "betterquesting:10": {
      "desc:8": "§7§oSimulates various types of player clicks.\n\nYou can cycle through the clicking type, left or right click, and what slot to use to perform the click.\n\n",
      "icon:10": {
        "Count:3": 1,
        "id:8": "extrautils2:user"
      },
      "name:8": "Mechanical User"
    }
  },
  "questID:3": 90197,
  "tasks:9": {
    "0:10": {
      "index:3": 0,
      "requiredItems:9": {
        "0:10": {
          "Count:3": 1,
          "id:8": "extrautils2:user"
        }
      },
      "taskID:8": "bq_standard:retrieval"
    }
  }
}