{
  "preRequisites:11": [
    114
  ],
  "properties:10": {
    "betterquesting:10": {
      "desc:8": "It is weird, but after encountering ice wizardry, I became aware of a calling from the cold...\nSomeone has used this type of magic to open a wormhole, and I want to know who it is!\n\n",
      "icon:10": {
        "Count:3": 1,
        "id:8": "divinerpg:snow_globe"
      },
      "name:8": "To the Icy Realm!"
    }
  },
  "questID:3": 203,
  "rewards:9": {
    "0:10": {
      "index:3": 0,
      "rewardID:8": "bq_standard:item",
      "rewards:9": {
        "0:10": {
          "Count:3": 64,
          "id:8": "divinerpg:snow_cones"
        }
      }
    }
  },
  "tasks:9": {
    "0:10": {
      "index:3": 0,
      "requiredItems:9": {
        "0:10": {
          "Count:3": 1,
          "id:8": "divinerpg:snow_globe"
        }
      },
      "taskID:8": "bq_standard:retrieval"
    }
  }
}