{
  "preRequisites:11": [
    63
  ],
  "properties:10": {
    "betterquesting:10": {
      "desc:8": "§7§oLooking for something in particular? more info in §cpersonal augmentation!",
      "icon:10": {
        "Count:3": 1,
        "id:8": "scannable:scanner"
      },
      "name:8": "Scanner"
    }
  },
  "questID:3": 87,
  "rewards:9": {
    "0:10": {
      "index:3": 0,
      "rewardID:8": "bq_standard:item",
      "rewards:9": {
        "0:10": {
          "Count:3": 1,
          "id:8": "scannable:module_range"
        },
        "1:10": {
          "Count:3": 1,
          "id:8": "iceandfire:goldpile",
          "tag:10": {
            "display:10": {
              "Name:8": "To search for underground dragons"
            }
          }
        },
        "2:10": {
          "Count:3": 1,
          "id:8": "iceandfire:silverpile",
          "tag:10": {
            "RepairCost:3": 0,
            "display:10": {
              "Name:8": "To search for underground dragons"
            }
          }
        },
        "3:10": {
          "Count:3": 1,
          "id:8": "iceandfire:copperpile",
          "tag:10": {
            "display:10": {
              "Name:8": "To search for undergroud dragons"
            }
          }
        }
      }
    }
  },
  "tasks:9": {
    "0:10": {
      "ignoreNBT:1": 1,
      "index:3": 0,
      "requiredItems:9": {
        "0:10": {
          "Count:3": 1,
          "id:8": "scannable:scanner"
        }
      },
      "taskID:8": "bq_standard:retrieval"
    }
  }
}