{
  "preRequisites:11": [
    20528
  ],
  "properties:10": {
    "betterquesting:10": {
      "desc:8": "激光滋滋滋\n水晶嗡嗡嗡\n使用红石火把右击以在接收红石信号停止工作和接收红石脉冲工作两种模式之间切换。\n可在前方放置压力板，机器设置为脉冲模式，以实现简单的自动化。",
      "icon:10": {
        "Count:3": 1,
        "id:8": "actuallyadditions:block_atomic_reconstructor"
      },
      "name:8": "原子再构机"
    }
  },
  "questID:3": 20563,
  "tasks:9": {
    "0:10": {
      "index:3": 0,
      "requiredItems:9": {
        "0:10": {
          "Count:3": 1,
          "id:8": "actuallyadditions:block_atomic_reconstructor"
        },
        "1:10": {
          "Count:3": 1,
          "id:8": "nae2:reconstruction_chamber"
        }
      },
      "taskID:8": "bq_standard:retrieval"
    }
  }
}