{
  "preRequisites:11": [
    20548
  ],
  "properties:10": {
    "betterquesting:10": {
      "desc:8": "9x9啊，懂的都懂……\n放置在解包机旁以进行自动合成。\n封包机需要位于AE网络中，不必与解包机相邻。",
      "icon:10": {
        "Count:3": 1,
        "id:8": "packagedexcrafting:ultimate_crafter"
      },
      "name:8": "终极封包合成器"
    }
  },
  "questID:3": 20717,
  "tasks:9": {
    "0:10": {
      "index:3": 0,
      "requiredItems:9": {
        "0:10": {
          "Count:3": 1,
          "id:8": "packagedexcrafting:ultimate_crafter"
        }
      },
      "taskID:8": "bq_standard:retrieval"
    }
  }
}