{
  "preRequisites:11": [
    20209
  ],
  "properties:10": {
    "betterquesting:10": {
      "desc:8": "通过深入研究通过使用更多注有炼金能量的材料，我可以将转化桌改造为便携形态，甚至能随身将其作为工作台使用。太实用了！",
      "icon:10": {
        "Count:3": 1,
        "id:8": "projecte:item.pe_transmutation_tablet"
      },
      "name:8": "奥术转化桌"
    }
  },
  "questID:3": 20351,
  "tasks:9": {
    "0:10": {
      "index:3": 0,
      "requiredItems:9": {
        "0:10": {
          "Count:3": 1,
          "id:8": "projectex:arcane_tablet"
        }
      },
      "taskID:8": "bq_standard:retrieval"
    }
  }
}