{
  "preRequisites:11": [
    50177
  ],
  "properties:10": {
    "betterquesting:10": {
      "desc:8": "消耗高级邪术材料（查看JEI配方）产出RF。\n魂石巨石块是相当便捷的可再生能量源。",
      "icon:10": {
        "Count:3": 1,
        "id:8": "modularmachinery:itemblueprint",
        "tag:10": {
          "dynamicmachine:8": "modularmachinery:empowered_monolith"
        }
      },
      "name:8": "注能巨石（良好）"
    }
  },
  "questID:3": 50188,
  "tasks:9": {
    "0:10": {
      "index:3": 0,
      "requiredItems:9": {
        "0:10": {
          "Count:3": 1,
          "id:8": "modularmachinery:itemblueprint",
          "tag:10": {
            "dynamicmachine:8": "modularmachinery:empowered_monolith"
          }
        }
      },
      "taskID:8": "bq_standard:retrieval"
    }
  }
}