{
  "preRequisites:11": [
    90095
  ],
  "properties:10": {
    "betterquesting:10": {
      "desc:8": "§7§oWireless routers and antennas can be used instead of multiple routers being connected by routing cables, if you want to connect Xnet setups, and share channels, wirelessly.\n\nThey work like regular routers, but they need energy.\n\nThe antenna base is placed on top of the wireless router.\n\nRegular antennas can be placed on top of the antenna base for short distance connections.\n\nAntenna dishes are used for large distance connections instead of antennas.",
      "icon:10": {
        "Count:3": 1,
        "id:8": "xnet:wireless_router"
      },
      "name:8": "Wireless Router"
    }
  },
  "questID:3": 90116,
  "tasks:9": {
    "0:10": {
      "index:3": 0,
      "requiredItems:9": {
        "0:10": {
          "Count:3": 1,
          "id:8": "xnet:wireless_router"
        },
        "1:10": {
          "Count:3": 1,
          "id:8": "xnet:antenna_base"
        },
        "2:10": {
          "Count:3": 1,
          "id:8": "xnet:antenna"
        },
        "3:10": {
          "Count:3": 1,
          "id:8": "xnet:antenna_dish"
        }
      },
      "taskID:8": "bq_standard:retrieval"
    }
  }
}