{
  "preRequisites:11": [
    1660051088
  ],
  "properties:10": {
    "betterquesting:10": {
      "desc:8": "伟大文明的功业。\n它们的错误，它们的遗憾。\n事件的叙事化。\n发生的改写。\n观点的投射。\n而在这一切面前的，是人。以及他们的故事，他们的历史。\n历史。\n对人的热爱，以及对其本性的承认。\n模式浮现。回响共振。类比成形。\n以及差异，分歧。\n不是一条直线。甚至不是一条循环的线。生命的美丽混沌，经由所有世代的人们传承。\n理序主的勇气，曾已失落，如今正在回归。",
      "icon:10": {
        "Count:3": 1,
        "id:8": "contenttweaker:seal_of_the_arbiter_historian"
      },
      "name:8": "史鉴"
    }
  },
  "questID:3": 1126830519,
  "tasks:9": {
    "0:10": {
      "index:3": 0,
      "requiredItems:9": {
        "0:10": {
          "Count:3": 1,
          "id:8": "contenttweaker:seal_of_the_arbiter_historian"
        }
      },
      "taskID:8": "bq_standard:retrieval"
    }
  }
}