{
  "preRequisites:11": [
    209
  ],
  "properties:10": {
    "betterquesting:10": {
      "desc:8": "我不明白缘由，但自从领悟植物魔法后，许多事情开始变得合理……\n我能感知到一些新事物，包括某些在泰拉游荡的生物留下的痕迹，它们与我一样通过虫洞来到此地……\n但现在，我能感知到它们穿越至此时，在时空中留下的“伤痕”……",
      "icon:10": {
        "Count:3": 1,
        "id:8": "divinerpg:arcana_portal_frame"
      },
      "name:8": "无尽要塞"
    }
  },
  "questID:3": 210,
  "rewards:9": {
    "0:10": {
      "index:3": 0,
      "rewardID:8": "bq_standard:item",
      "rewards:9": {
        "0:10": {
          "Count:3": 4,
          "id:8": "contenttweaker:pan_di_stelle"
        },
        "1:10": {
          "Count:3": 1,
          "id:8": "contenttweaker:diary_of_a_realmshifter"
        }
      }
    }
  },
  "tasks:9": {
    "0:10": {
      "index:3": 0,
      "requiredItems:9": {
        "0:10": {
          "Count:3": 1,
          "id:8": "divinerpg:arcana_portal_frame"
        }
      },
      "taskID:8": "bq_standard:retrieval"
    }
  }
}