{
  "preRequisites:11": [
    209
  ],
  "properties:10": {
    "betterquesting:10": {
      "desc:8": "I do not understand why, but after becoming aware of botanical magic, things make more sense...\nI can feel new things, including traces, traces left by some of the creatures roaming Terra, they came here through wormholes, just like me...\nBut now I can sense the \u0027scars\u0027 into spacetime they left while travelling here...",
      "icon:10": {
        "Count:3": 1,
        "id:8": "divinerpg:arcana_portal_frame"
      },
      "name:8": "The Infinite Fortress"
    }
  },
  "questID:3": 210,
  "rewards:9": {
    "0:10": {
      "index:3": 0,
      "rewardID:8": "bq_standard:item",
      "rewards:9": {
        "0:10": {
          "Count:3": 4,
          "id:8": "contenttweaker:pan_di_stelle"
        },
        "1:10": {
          "Count:3": 1,
          "id:8": "contenttweaker:diary_of_a_realmshifter"
        }
      }
    }
  },
  "tasks:9": {
    "0:10": {
      "index:3": 0,
      "requiredItems:9": {
        "0:10": {
          "Count:3": 1,
          "id:8": "divinerpg:arcana_portal_frame"
        }
      },
      "taskID:8": "bq_standard:retrieval"
    }
  }
}