{
  "preRequisites:11": [
    203
  ],
  "properties:10": {
    "betterquesting:10": {
      "desc:8": "§o§7发现于冰晶雪原地下的地牢！\n\n§f不仅有人能使用巫术开启虫洞，这位“冰霜主宰”甚至能以伟力征服整颗行星，将其化作永恒的冰封冻土。",
      "icon:10": {
        "Count:3": 1,
        "id:8": "divinerpg:snowflake"
      },
      "name:8": "冰雪之力"
    }
  },
  "questID:3": 217,
  "rewards:9": {
    "0:10": {
      "index:3": 0,
      "rewardID:8": "bq_standard:item",
      "rewards:9": {
        "0:10": {
          "Count:3": 1,
          "Damage:2": 1,
          "id:8": "projecte:item.pe_matter"
        },
        "1:10": {
          "Count:3": 1,
          "id:8": "simple_trophies:trophy",
          "tag:10": {
            "TrophyColorBlue:3": 1,
            "TrophyColorGreen:3": 1,
            "TrophyColorRed:3": 1,
            "TrophyItem:10": {
              "Count:1": 1,
              "Damage:2": 0,
              "id:8": "divinerpg:snowflake"
            },
            "TrophyName:8": "射手屠戮者",
            "TrophyShowsTooltip:1": 1,
            "TrophyVariant:8": "classic"
          }
        }
      }
    }
  },
  "tasks:9": {
    "0:10": {
      "index:3": 0,
      "requiredItems:9": {
        "0:10": {
          "Count:3": 1,
          "id:8": "divinerpg:snowflake"
        }
      },
      "taskID:8": "bq_standard:retrieval"
    }
  }
}