{
  "preRequisites:11": [
    2168
  ],
  "properties:10": {
    "betterquesting:10": {
      "desc:8": "确实，暮光部落尚未被击败，但这次打击确实产生了积极效果！\n蜜蜂成功从历战浮游者那里夺取，并模仿了部分灵魂操纵能力，现在正在研究如何将其用于善途。当然，这取决于它们对“善”的定义。\n毕竟，共鸣界当前的状况就是它们的杰作……",
      "icon:10": {
        "Count:3": 1,
        "Damage:2": 14020,
        "id:8": "gendustry:honey_comb"
      },
      "name:8": "吸干灵魂，唉就和直播差不多"
    }
  },
  "questID:3": 2220,
  "tasks:9": {
    "0:10": {
      "index:3": 0,
      "requiredItems:9": {
        "0:10": {
          "Count:3": 1,
          "id:8": "contenttweaker:soulsucking_callstone"
        },
        "1:10": {
          "Count:3": 1,
          "Damage:2": 14020,
          "id:8": "gendustry:honey_comb"
        }
      },
      "taskID:8": "bq_standard:retrieval"
    }
  }
}