{
  "preRequisites:11": [
    325
  ],
  "properties:10": {
    "betterquesting:10": {
      "desc:8": "情况或许正变得有些危险，但我对定义物质的材料性能有着绝对信心。\n我不仅能禁锢高能物体，还能约束高密度物体，甚至是无限密度的物体。\n我可以制造出属于自己的黑洞；一个小型黑洞，却能让我直接将机械放置在事件视界边缘。\n极端的潮汐力会引发一种奇异的相变：可控的意大利面化效应。\n说实话，除了科学实验，我甚至不确定这种现象能有什么实际用途。\n我必须承认，这在很大程度上是一项为了攀比而完成的作品。创造出强能界奇点的，是一种强大的魔法，它的存在让我无比好奇。我想知道，自己究竟能将塞德娜金属与定义物质的性能推到何种极限。\n这是我最宏大的技术成就，也极有可能是我毕生所能研发出的最尖端科技。\n而现在，该为它找到用武之地了……",
      "icon:10": {
        "Count:3": 1,
        "id:8": "contenttweaker:miniature_black_hole"
      },
      "name:8": "戴森压缩器"
    }
  },
  "questID:3": 326,
  "tasks:9": {
    "0:10": {
      "index:3": 0,
      "requiredItems:9": {
        "0:10": {
          "Count:3": 1,
          "id:8": "contenttweaker:horizon_stabilizer"
        },
        "1:10": {
          "Count:3": 1,
          "id:8": "contenttweaker:infinity_dyson_conduit"
        },
        "2:10": {
          "Count:3": 1,
          "id:8": "contenttweaker:dyson_compressor"
        },
        "3:10": {
          "Count:3": 1,
          "id:8": "contenttweaker:black_hole_core"
        }
      },
      "taskID:8": "bq_standard:retrieval"
    },
    "1:10": {
      "index:3": 1,
      "requiredItems:9": {
        "0:10": {
          "Count:3": 1,
          "id:8": "modularmachinery:itemblueprint",
          "tag:10": {
            "dynamicmachine:8": "modularmachinery:dyson_compressor"
          }
        }
      },
      "taskID:8": "bq_standard:optional_retrieval"
    }
  }
}