{
  "preRequisites:11": [
    136
  ],
  "properties:10": {
    "betterquesting:10": {
      "desc:8": "§7§o对女爵祭坛使用术士宝石来召唤女爵。\n\n对蜂王祭坛使用蜂巢卵来召唤蜂王。\n\n§f爵士维度是个宗教氛围极其浓厚的星球，而他们的信仰绝非平和之流！\n当然，他们那位战争之神的化身……都是递归大师……\n在我见识过的诸多力量体系中，递归是最耐人寻味的一种。在无数次旅途中，我尝试为不同魔法场域构建某种依存层级，试图厘清它们之间的从属关系。\n比如查伽洛斯这头怪物展现的诡谲力量，看似依托于灵气场域与特定源质的运用，最终呈现的却绝非神秘使法术的形态。它虽以神秘学为基础，表现方式却大相径庭，就像引力本质是时空场的扭曲，呈现的却是加速度的表象。若非如此，人类早在爱因斯坦之前就该参透其中奥秘。\n正因如此，若要在魔法研习中精进，建立这种层级体系至关重要。\n但递归却是个异类。它的运作机理让我想起永不停摆的钟锤。触发递归效应的永远是另一个递归效应，就像在宇宙虚空中永续传播的光。但就算是光，遭遇物质也终会耗散能量。递归却能凭空持续。\n我总能卷土重来，我的敌人们也是……幸好他们回归的速度远不及我。",
      "icon:10": {
        "Count:3": 1,
        "id:8": "contenttweaker:barathos_cap"
      },
      "name:8": "攻陷爵士维度"
    }
  },
  "questID:3": 343,
  "rewards:9": {
    "0:10": {
      "index:3": 0,
      "rewardID:8": "bq_standard:item",
      "rewards:9": {
        "0:10": {
          "Count:3": 1,
          "id:8": "simple_trophies:trophy",
          "tag:10": {
            "TrophyColorBlue:3": 0,
            "TrophyColorGreen:3": 0,
            "TrophyColorRed:3": 0,
            "TrophyItem:10": {
              "Count:1": 1,
              "Damage:2": 0,
              "id:8": "contenttweaker:hive_king_tendril"
            },
            "TrophyName:8": "蜂王屠戮者",
            "TrophyShowsTooltip:1": 1,
            "TrophyVariant:8": "classic"
          }
        },
        "1:10": {
          "Count:3": 1,
          "id:8": "simple_trophies:trophy",
          "tag:10": {
            "TrophyColorBlue:3": 0,
            "TrophyColorGreen:3": 0,
            "TrophyColorRed:3": 0,
            "TrophyItem:10": {
              "Count:1": 1,
              "Damage:2": 0,
              "id:8": "contenttweaker:baroness_brain"
            },
            "TrophyName:8": "女爵屠戮者",
            "TrophyShowsTooltip:1": 1,
            "TrophyVariant:8": "classic"
          }
        }
      }
    }
  },
  "tasks:9": {
    "0:10": {
      "index:3": 0,
      "requiredItems:9": {
        "0:10": {
          "Count:3": 1,
          "id:8": "contenttweaker:barathos_cap"
        }
      },
      "taskID:8": "bq_standard:retrieval"
    }
  }
}