{
  "preRequisites:11": [
    389
  ],
  "properties:10": {
    "betterquesting:10": {
      "desc:8": "§7§o团块可通过递归方式生成。若需大量获取，可通过漏斗、投掷器与红石时钟实现伪自动化。\n\n§f我无法确知所为是否良善，但仍可怀抱善念。\n我是自由的。\n我活在递归的宿命中，这宿命由妄图囚禁我者赐予。我被迫卷入无法回避的战争，履行着从未知晓的预言。\n但我依然自由。\n本可放弃抵抗，本可认定行动毫无意义，本可就此放手。但我选择继续前行。\n在此抉择中，我掌握自主权。在此抉择中，我获得自由。\n我是自由的。纵使人生混沌唯有向前，我仍是自由的。",
      "icon:10": {
        "Count:3": 1,
        "id:8": "divinerpg:teaker_lump"
      },
      "name:8": "递归凝团"
    }
  },
  "questID:3": 392,
  "tasks:9": {
    "0:10": {
      "index:3": 0,
      "requiredItems:9": {
        "0:10": {
          "Count:3": 1,
          "id:8": "divinerpg:teaker_lump"
        }
      },
      "taskID:8": "bq_standard:retrieval"
    }
  }
}