{
  "preRequisites:11": [
    286
  ],
  "properties:10": {
    "betterquesting:10": {
      "desc:8": "虽然尚未完全理解，但将熵发挥至极限的关键确实潜藏于泰拉巨龙的心脏之中。或者说，存在于某个能同时现身于多重位面的强大巨龙体内。\n当物质积累的熵突破某个本不可企及、却因魔法干预而达成的临界阈值时，其基础粒子将呈现量子场论预测的所有可能构型；换言之，达成真正的混沌态。\n处于此态的晶体若获得充足能量，便可自我复制增殖。因此即便尚未参透其本源原理，我也能通过不断获取更多样本展开研究。",
      "icon:10": {
        "Count:3": 1,
        "Damage:2": 1,
        "id:8": "draconicevolution:draconium_block"
      },
      "name:8": "混沌"
    }
  },
  "questID:3": 426,
  "tasks:9": {
    "0:10": {
      "index:3": 0,
      "requiredItems:9": {
        "0:10": {
          "Count:3": 1,
          "id:8": "contenttweaker:charged_draconium_block"
        }
      },
      "taskID:8": "bq_standard:retrieval"
    },
    "1:10": {
      "index:3": 1,
      "requiredItems:9": {
        "0:10": {
          "Count:3": 1,
          "id:8": "modularmachinery:itemblueprint",
          "tag:10": {
            "dynamicmachine:8": "modularmachinery:chaotic_condenser"
          }
        }
      },
      "taskID:8": "bq_standard:optional_retrieval"
    }
  }
}