{
  "preRequisites:11": [
    272
  ],
  "properties:10": {
    "betterquesting:10": {
      "desc:8": "§7§o这是海贼王的梗吗？！？\n\n§f看来我并非首个造访此星球的“蜜蜂冠军”。我的前任留下了一件武器。\n秉承蜜蜂一贯作风，他们不会直接透露秘密，我必须先证明自己的价值。通过这项新试炼后，他们终于提供了关键情报。\n我的敌人们掌握着全宇宙最强大的力量之一。这固然令人畏惧，但正因如此，历代对抗这些力量的战斗都被详尽记录了下来。通过分析数千场魔法与科技战争的交锋数据，某些规律逐渐明晰。\n若想直面暮光部落这等真正的宇宙伟力，自身必须获得同等实力，这是无可回避的铁律。在绝大多数记载中，绝对力量总能碾压智谋与策略。\n根据这些浩瀚记载，获得此等力量需要遵循特定步骤。铼界蜜蜂告诉我，第一步就是我已获得的递归不朽。第二步则需要能斩断递归的强力武器，后续步骤有待探索。\n泰拉传说中的附魔长弓虽具此效，但要对抗真正强大的递归存在，还需其他武器。他们透露，其中一件正是其陨落盟友的遗物。\n蜜蜂坦言此物尚不足以终结战争，但确是攀登更高境界的必要阶梯。",
      "icon:10": {
        "Count:3": 1,
        "id:8": "extrautils2:lawsword"
      },
      "name:8": "昔日勇士的遗物"
    }
  },
  "questID:3": 510,
  "rewards:9": {
    "0:10": {
      "index:3": 0,
      "rewardID:8": "bq_standard:item",
      "rewards:9": {
        "0:10": {
          "Count:3": 1,
          "id:8": "minecraft:enchanted_book",
          "tag:10": {
            "StoredEnchantments:9": {
              "0:10": {
                "id:3": 101,
                "lvl:2": 3
              }
            }
          }
        }
      }
    }
  },
  "tasks:9": {
    "0:10": {
      "index:3": 0,
      "requiredItems:9": {
        "0:10": {
          "Count:3": 1,
          "id:8": "extrautils2:lawsword"
        }
      },
      "taskID:8": "bq_standard:retrieval"
    },
    "1:10": {
      "index:3": 1,
      "requiredItems:9": {
        "0:10": {
          "Count:3": 1,
          "id:8": "contenttweaker:puzzle_solution_kikoku"
        }
      },
      "taskID:8": "bq_standard:optional_retrieval"
    }
  }
}