{
  "preRequisites:11": [
    81569973,
    471525021
  ],
  "properties:10": {
    "betterquesting:10": {
      "desc:8": "",
      "icon:10": {
        "Count:3": 1,
        "id:8": "aoa3:flaming_fury",
        "tag:10": {
          "HideFlags:1": 2
        }
      },
      "name:8": "Flaming Fury"
    }
  },
  "questID:3": 467612206,
  "tasks:9": {
    "0:10": {
      "index:3": 0,
      "requiredItems:9": {
        "0:10": {
          "Count:3": 1,
          "id:8": "aoa3:flaming_fury",
          "tag:10": {
            "HideFlags:1": 2
          }
        }
      },
      "taskID:8": "bq_standard:retrieval"
    }
  }
}