{
  "preRequisites:11": [
    20415
  ],
  "properties:10": {
    "betterquesting:10": {
      "desc:8": "§7§o以下任务展示了处理和饲养鸡的方法！\n\n§f基因编辑鸡，因为我想干什么就他*干什么……",
      "icon:10": {
        "Count:3": 1,
        "Damage:2": 31,
        "id:8": "botania:cosmetic"
      },
      "name:8": "无以卵比"
    }
  },
  "questID:3": 20424,
  "tasks:9": {
    "0:10": {
      "index:3": 0,
      "requiredItems:9": {
        "0:10": {
          "Count:3": 1,
          "id:8": "minecraft:wheat_seeds"
        }
      },
      "taskID:8": "bq_standard:retrieval"
    }
  }
}