{
  "preRequisites:11": [
    20255
  ],
  "properties:10": {
    "betterquesting:10": {
      "desc:8": "§7§o使用门钥匙。",
      "icon:10": {
        "Count:3": 1,
        "id:8": "abyssalcraft:fusedabyssalsand"
      },
      "name:8": "深渊荒原"
    }
  },
  "questID:3": 20269,
  "tasks:9": {
    "0:10": {
      "dimension:3": 50,
      "hideInfo:1": 1,
      "index:3": 0,
      "name:8": "深渊荒原",
      "taskID:8": "bq_standard:location"
    },
    "1:10": {
      "index:3": 1,
      "requiredItems:9": {
        "0:10": {
          "Count:3": 1,
          "id:8": "abyssalcraft:fusedabyssalsand"
        }
      },
      "taskID:8": "bq_standard:optional_retrieval"
    }
  }
}