{
  "preRequisites:11": [
    20285
  ],
  "properties:10": {
    "betterquesting:10": {
      "desc:8": "ยง7ยงo5 x 6 frame of ancient rock with one rune of power, direction, space, reality, travel (right click power with realmstone)",
      "icon:10": {
        "Count:3": 1,
        "id:8": "aoa3:precasia_grass"
      },
      "name:8": "Precasia Forest"
    }
  },
  "questID:3": 20289,
  "tasks:9": {
    "0:10": {
      "dimension:3": 818,
      "hideInfo:1": 1,
      "index:3": 0,
      "name:8": "Precasia Forest",
      "taskID:8": "bq_standard:location"
    },
    "1:10": {
      "index:3": 1,
      "requiredItems:9": {
        "0:10": {
          "Count:3": 1,
          "id:8": "aoa3:precasia_grass"
        }
      },
      "taskID:8": "bq_standard:optional_retrieval"
    }
  }
}