{
  "preRequisites:11": [
    1007
  ],
  "properties:10": {
    "betterquesting:10": {
      "desc:8": "§7§oThe genetic transposer has two main functions.\n\nFirst, it can be used to duplicate gene samples, combine a blank one with an imprinted one to duplicate it! This is how you can farm the ingredients to craft the torcherino!\n\nSecond, you can combine genetic samples into templates, these will be used to customize your bees!\n\nNOTE: templates do not need to have all 12 genes! You can make templates with even one chromosome!",
      "icon:10": {
        "Count:3": 1,
        "id:8": "gendustry:sampler"
      },
      "name:8": "Genetic Transposer"
    }
  },
  "questID:3": 20488,
  "tasks:9": {
    "0:10": {
      "ignoreNBT:1": 1,
      "index:3": 0,
      "requiredItems:9": {
        "0:10": {
          "Count:3": 1,
          "id:8": "gendustry:transposer"
        }
      },
      "taskID:8": "bq_standard:retrieval"
    }
  }
}